flask_blog/__about__.py
flask_blog/__init__.py
flask_blog/translations/__init__.py
flask_blog-0.0.1.dist-info/METADATA
flask_blog-0.0.1.dist-info/WHEEL
flask_blog-0.0.1.dist-info/licenses/LICENSE.rst
flask_blog-0.0.1.dist-info/RECORD
