Metadata-Version: 2.3
Name: Flask-Blog
Version: 0.0.1
Summary: Build a blog with Flask.
Project-URL: Documentation, https://flask-blog.readthedocs.io
Project-URL: Source, https://github.com/ojso/flask-blog
Project-URL: Homepage, https://github.com/ojso/flask-blog
Project-URL: Issues, https://github.com/ojso/flask-blog/issues
Author-email: huadong <david.dong.hua@gmail.com>
License: MIT License
License-File: LICENSE.rst
Keywords: blog,flask
Classifier: Development Status :: 3 - Alpha
Classifier: Environment :: Web Environment
Classifier: Framework :: Flask
Classifier: Intended Audience :: Developers
Classifier: License :: OSI Approved :: MIT License
Classifier: Programming Language :: Python
Classifier: Programming Language :: Python :: 3
Classifier: Programming Language :: Python :: 3.10
Classifier: Programming Language :: Python :: 3.11
Classifier: Topic :: Software Development :: Build Tools
Requires-Python: >=3.10
Requires-Dist: flask-exts>=0.1
Requires-Dist: python-dotenv>=1.0
